openweather_mcp-0.1.0.dist-info/METADATA
openweather_mcp-0.1.0.dist-info/WHEEL
openweather_mcp-0.1.0.dist-info/entry_points.txt
openweather_mcp-0.1.0.dist-info/licenses/LICENSE
openweather_mcp/__init__.py
openweather_mcp/errors.py
openweather_mcp/server.py
openweather_mcp/structs.py
openweather_mcp-0.1.0.dist-info/RECORD
