Metadata-Version: 2.1
Name: openweather-mcp
Version: 0.1.0
Summary: A Model Context Protocal server for OpenWeather.org API.
Keywords: mcp
Author-Email: Frost Ming <me@frostming.com>
License: MIT
Classifier: Intended Audience :: Developers
Classifier: Intended Audience :: Science/Research
Classifier: License :: OSI Approved :: MIT License
Classifier: Programming Language :: Python :: 3
Requires-Python: >=3.10
Requires-Dist: mcp>=1
Requires-Dist: httpx>=0.28.1
Requires-Dist: pydantic>=2.11.3
